ace_tools_open/__init__.py
ace_tools_open/display.py
ace_tools_open-0.1.0.dist-info/LICENSE
ace_tools_open-0.1.0.dist-info/METADATA
ace_tools_open-0.1.0.dist-info/WHEEL
ace_tools_open-0.1.0.dist-info/top_level.txt
ace_tools_open-0.1.0.dist-info/RECORD
