Metadata-Version: 2.1
Name: ace_tools_open
Version: 0.1.0
Summary: Open implementation of ace_tools referenced in GPT4o
Home-page: https://github.com/zinccat/ace_tools_open
Author: ZincCat
Author-email: ZincCat <zincchloride@outlook.com>
License: MIT
Project-URL: Homepage, https://github.com/zinccat/ace_tools_open
Requires-Python: >=3.6
License-File: LICENSE
Requires-Dist: pandas
Requires-Dist: itables
Requires-Dist: IPython
Provides-Extra: dev
Requires-Dist: pytest; extra == "dev"
